verilog/problem6.v
module problem6(
  input i_clk,
  input i_rst,
  input [15:0] i_data,
  output reg [2:0] o_data
);

  always @(posedge i_clk) begin
    if(i_rst) begin
      o_data = 3'b000;
    end else begin
      case(i_data[1:0])
        2'b00 : o_data = i_data[4:2];
        2'b01 : o_data = i_data[7:5];
        2'b10 : o_data = i_data[10:8];
        2'b11 : o_data = i_data[13:11];
      endcase
    end
  end
endmodule

verilog/problem6_tb.v
module problem6_tb;
  reg i_clk = 0;
  reg i_rst = 0;
  reg [15:0] i_data = 16'b0010001101000100;
  wire [2:0] o_p;

  initial begin
    $dumpfile("wave.vcd");
    $dumpvars(0, DUT);
  end

  problem6 DUT(
    .i_clk (i_clk),
    .i_rst (i_rst),
    .i_data (i_data),
    .o_data (o_p)
  );

  always #1 begin
    i_clk = ~i_clk;
  end

  initial begin
    i_data[1:0] = 2'b00;
    #10
    $display("i_data: %016b, o_data: %03b", i_data, o_p);
    i_data[1:0] = 2'b01;
    #10
    $display("i_data: %016b, o_data: %03b", i_data, o_p);
    i_data[1:0] = 2'b10;
    $display("i_data: %016b, o_data: %03b", i_data, o_p);
    i_data[1:0] = 2'b11;
    #10
    $display("i_data: %016b, o_data: %03b", i_data, o_p);
    i_rst = 1'b1;
    #10
    $display("i_data: %016b, o_data: %03b", i_data, o_p);
    $finish;
  end

endmodule

verilog/wave.vcd
$date
	Sun Sep 10 18:43:36 2023
$end
$version
	Icarus Verilog
$end
$timescale
	1s
$end
$scope module problem6_tb $end
$scope module DUT $end
$var wire 1 ! i_clk $end
$var wire 16 " i_data [15:0] $end
$var wire 1 # i_rst $end
$var reg 3 $ o_data [2:0] $end
$upscope $end
$upscope $end
$enddefinitions $end
#0
$dumpvars
bx $
0#
b10001101000100 "
0!
$end
#1
b1 $
1!
#2
0!
#3
1!
#4
0!
#5
1!
#6
0!
#7
1!
#8
0!
#9
1!
#10
0!
b10001101000101 "
#11
b10 $
1!
#12
0!
#13
1!
#14
0!
#15
1!
#16
0!
#17
1!
#18
0!
#19
1!
#20
0!
b10001101000111 "
#21
b100 $
1!
#22
0!
#23
1!
#24
0!
#25
1!
#26
0!
#27
1!
#28
0!
#29
1!
#30
0!
1#
#31
b0 $
1!
